{
  "gitSyncId": "655b663c44c3196dff1b331d_65fbe7de427a0f605ee13d54",
  "id": "Dashboard_GithubUtils.getProductDependanciesGithub",
  "pluginId": "js-plugin",
  "pluginType": "JS",
  "unpublishedAction": {
    "actionConfiguration": {
      "encodeParamsToggle": true,
      "jsArguments": [],
      "paginationType": "NONE",
      "timeoutInMillisecond": 10000
    },
    "collectionId": "Dashboard_GithubUtils",
    "confirmBeforeExecute": false,
    "datasource": {
      "isAutoGenerated": false,
      "name": "UNUSED_DATASOURCE",
      "pluginId": "js-plugin"
    },
    "dynamicBindingPathList": [
      {
        "key": "body"
      }
    ],
    "executeOnLoad": false,
    "fullyQualifiedName": "GithubUtils.getProductDependanciesGithub",
    "name": "getProductDependanciesGithub",
    "pageId": "Dashboard",
    "userSetOnLoad": false
  }
}